is_bcg_network/__init__.py
is_bcg_network/logic.py
is_bcg_network-0.1.4.dist-info/entry_points.txt
is_bcg_network-0.1.4.dist-info/WHEEL
is_bcg_network-0.1.4.dist-info/METADATA
is_bcg_network-0.1.4.dist-info/RECORD
