Metadata-Version: 2.1
Name: is-bcg-network
Version: 0.1.4
Summary: one line import to know if you are running inside the BCG network
License: MIT
Author: Niels Freier
Author-email: freier.niels@bcg.com
Requires-Python: >=3.5,<4.0
Classifier: License :: OSI Approved :: MIT License
Classifier: Programming Language :: Python :: 3
Classifier: Programming Language :: Python :: 3.5
Classifier: Programming Language :: Python :: 3.6
Classifier: Programming Language :: Python :: 3.7
Classifier: Programming Language :: Python :: 3.8
Classifier: Programming Language :: Python :: 3.9
